jeong_lotto/__init__.py
jeong_lotto/lotto.py
jeong_lotto-0.2.0.dist-info/METADATA
jeong_lotto-0.2.0.dist-info/WHEEL
jeong_lotto-0.2.0.dist-info/entry_points.txt
jeong_lotto-0.2.0.dist-info/top_level.txt
jeong_lotto-0.2.0.dist-info/RECORD
