Metadata-Version: 2.1
Name: jeong_lotto
Version: 0.2.0
Summary: Default template for PDM package
Author-email: Jeonghoon2 <ukidd12@naver.com>
License: MIT
Requires-Python: >=3.9
